setup.py
socks6/__init__.py
socks6.egg-info/PKG-INFO
socks6.egg-info/SOURCES.txt
socks6.egg-info/dependency_links.txt
socks6.egg-info/top_level.txt