Metadata-Version: 1.0
Name: socks6
Version: 0.0.0
Summary: SOCKSv6 bring your own io library. 
Home-page: https://github.com/mohanson/socks6
Author: mohanson
Author-email: mohanson@outlook.com
License: PSF
Platform: UNKNOWN
